evogression/__init__.py
evogression/_version.py
evogression/data.py
evogression/evolution.py
evogression/groups.py
evogression/rust_evogression.cp311-win_amd64.pyd
tests/__init__.py
tests/data_examples.py
tests/evolution_test.py
tests/fitting_test.py
tests/group_test.py
tests/output_eqn_test.py
tests/parameter_pruning_test.py
tests/surface_evolution_test.py
tests/surface_group_test.py
evogression-0.11.0.dist-info/LICENSE.txt
evogression-0.11.0.dist-info/METADATA
evogression-0.11.0.dist-info/WHEEL
evogression-0.11.0.dist-info/top_level.txt
evogression-0.11.0.dist-info/RECORD
