Metadata-Version: 2.1
Name: evogression
Version: 0.11.0
Summary: Evolutionary Regression
Home-page: https://github.com/zachbateman/evogression.git
Download-URL: https://github.com/zachbateman/evogression/archive/v_0.11.0.tar.gz
Author: Zach Bateman
License: MIT
Keywords: REGRESSION,MACHINE,LEARNING,EVOLUTION
Classifier: Development Status :: 4 - Beta
Classifier: License :: OSI Approved :: MIT License
Classifier: Programming Language :: Python :: 3.10
Classifier: Programming Language :: Python :: 3.11
Classifier: Programming Language :: Python :: 3.12
License-File: LICENSE.txt
Requires-Dist: pandas
